utrc/__init__.py
utrc/_modidx.py
utrc/attr.py
utrc/atyp.py
utrc/bend.py
utrc/cols.py
utrc/cons.py
utrc/data.py
utrc/diff.py
utrc/dims.py
utrc/init.py
utrc/kwds.py
utrc/logs.py
utrc/loss.py
utrc/misc.py
utrc/pand.py
utrc/perc.py
utrc/seed.py
utrc/smpl.py
utrc/strs.py
utrc/tens.py
utrc/util.py
utrc-0.0.13.dist-info/LICENSE
utrc-0.0.13.dist-info/METADATA
utrc-0.0.13.dist-info/WHEEL
utrc-0.0.13.dist-info/entry_points.txt
utrc-0.0.13.dist-info/top_level.txt
utrc-0.0.13.dist-info/RECORD
